{
  "model_name_or_path": "google/t5-v1_1-base",
  "cache_dir": "cache",
  "experiment_name": "sdt_sgd_baseline_v0",
  "train_file": [
    "data/processed/SGD_SDT/v0/train/version_1/data.json"
  ],
  "validation_file": "data/processed/SGD_SDT/v0/dev/version_1/data.json",
  "validation_ref_dir": "data/raw/original/dev",
  "validation_template_dir": "data/interim/blank_dialogue_templates/original/dev",
  "preprocessing_num_workers": 128,
  "optimizer": "adafactor",
  "learning_rate": 0.0001,
  "use_scheduler": true,
  "scheduler_warmup_steps": 1000,
  "log_level": "info",
  "gradient_accumulation_steps": 1,
  "per_device_train_batch_size": 16,
  "per_device_eval_batch_size": 200,
  "ddp_find_unused_parameters": false,
  "do_train": true,
  "group_by_length": true,
  "tf32": true,
  "bf16": true,
  "do_eval": false,
  "predict_with_generate": true,
  "logging_first_step": true,
  "logging_steps": 5000,
  "lr_log_freq": 100,
  "eval_steps": 5000,
  "save_steps": 5000,
  "early_stopping_patience": 3,
  "load_best_model_at_end": true,
  "report_to": "wandb",
  "wandb_entity": "ankitbhattarai",
  "wandb_project": "robust-dst",
  "wandb_log_model": true,
  "seed": 20240130,
  "num_train_epochs": 5,
  "max_source_length": 2048,
  "max_target_length": 512,
  "val_max_target_length": 512,
  "ensure_determinism": true,
  "overwrite_cache": true,
  "source_column": "source",
  "target_column": "target"
}
